Sherpa.py
_Sherpa.so
bin/Sherpa
bin/Sherpa-config
bin/Sherpa-generate-model
bin/init_nlo.sh
bin/plot_stats.sh
include/SHERPA-MC/AHADIC++/Decays/Cluster_Decay_Analysis.H
include/SHERPA-MC/AHADIC++/Decays/Cluster_Decayer.H
include/SHERPA-MC/AHADIC++/Decays/Cluster_Splitter.H
include/SHERPA-MC/AHADIC++/Formation/Beam_Particles_Shifter.H
include/SHERPA-MC/AHADIC++/Formation/Gluon_Decayer.H
include/SHERPA-MC/AHADIC++/Formation/Gluon_Splitter.H
include/SHERPA-MC/AHADIC++/Formation/Singlet_Checker.H
include/SHERPA-MC/AHADIC++/Formation/Singlet_Former.H
include/SHERPA-MC/AHADIC++/Formation/Trivial_Splitter.H
include/SHERPA-MC/AHADIC++/Main/Ahadic.H
include/SHERPA-MC/AHADIC++/Tools/Cluster.H
include/SHERPA-MC/AHADIC++/Tools/Constituents.H
include/SHERPA-MC/AHADIC++/Tools/Double_Transitions.H
include/SHERPA-MC/AHADIC++/Tools/Flavour_Selector.H
include/SHERPA-MC/AHADIC++/Tools/Hadron_Multiplet.H
include/SHERPA-MC/AHADIC++/Tools/Hadronisation_Parameters.H
include/SHERPA-MC/AHADIC++/Tools/KT_Selector.H
include/SHERPA-MC/AHADIC++/Tools/Multiplet_Constructor.H
include/SHERPA-MC/AHADIC++/Tools/Proto_Particle.H
include/SHERPA-MC/AHADIC++/Tools/Single_Transitions.H
include/SHERPA-MC/AHADIC++/Tools/Singlet_Tools.H
include/SHERPA-MC/AHADIC++/Tools/Soft_Cluster_Handler.H
include/SHERPA-MC/AHADIC++/Tools/Splitter_Base.H
include/SHERPA-MC/AHADIC++/Tools/Splitting_Tools.H
include/SHERPA-MC/AHADIC++/Tools/Wave_Function.H
include/SHERPA-MC/AHADIC++/Tools/Z_Selector.H
include/SHERPA-MC/AMEGIC++/Amplitude/Amplitude_Base.H
include/SHERPA-MC/AMEGIC++/Amplitude/Amplitude_Generator.H
include/SHERPA-MC/AMEGIC++/Amplitude/Amplitude_Group.H
include/SHERPA-MC/AMEGIC++/Amplitude/Amplitude_Handler.H
include/SHERPA-MC/AMEGIC++/Amplitude/Amplitude_Manipulator.H
include/SHERPA-MC/AMEGIC++/Amplitude/Amplitude_Output.H
include/SHERPA-MC/AMEGIC++/Amplitude/CFColor.H
include/SHERPA-MC/AMEGIC++/Amplitude/Color_Generator.H
include/SHERPA-MC/AMEGIC++/Amplitude/Color_Group.H
sherpa_mc-3.0.3b1.dist-info/METADATA
sherpa_mc-3.0.3b1.dist-info/WHEEL
sherpa_mc-3.0.3b1.dist-info/licenses/COPYING
sherpa_mc-3.0.3b1.dist-info/licenses/LICENCE
sherpa_mc-3.0.3b1.dist-info/licenses/AUTHORS
sherpa_mc-3.0.3b1.dist-info/RECORD
