Metadata-Version: 2.2
Name: sherpa-mc
Version: 3.0.3b1
Summary: The Sherpa event generator for High Energy Physics
Keywords: sherpa
Author-Email: "Enrico Bothmann et al." <sherpa@projects.hepforge.org>
License: GPLv3 License
Classifier: Intended Audience :: Science/Research
Classifier: License :: OSI Approved :: GNU General Public License v3 (GPLv3)
Classifier: Operating System :: POSIX :: Linux
Requires-Python: >=3.8
